meuscontrolesflet2/__init__.py
meuscontrolesflet2/meus_controles.py
meuscontrolesflet2-0.2.41.dist-info/METADATA
meuscontrolesflet2-0.2.41.dist-info/WHEEL
meuscontrolesflet2-0.2.41.dist-info/RECORD
