Metadata-Version: 2.1
Name: meuscontrolesflet2
Version: 0.2.41
Summary: 
Author: leomoraesguitar
Author-email: 123950901+leomoraesguitar@users.noreply.github.com
Requires-Python: >=3.11,<4.0
Classifier: Programming Language :: Python :: 3
Classifier: Programming Language :: Python :: 3.11
Classifier: Programming Language :: Python :: 3.12
Requires-Dist: flet (>=0.23.0,<0.24.0)
Requires-Dist: keyboard (>=0.13.5,<0.14.0)
Requires-Dist: pandas (>=2.2.2,<3.0.0)
Requires-Dist: pyautogui (>=0.9.54,<0.10.0)
